LICENSE
MANIFEST.in
README.md
setup.py
environments_utils/__init__.py
environments_utils/__version__.py
environments_utils/available_instructions.py
environments_utils/has_gpu.py
environments_utils/is_architecture.py
environments_utils/is_cluster.py
environments_utils/is_colab.py
environments_utils/is_notebook.py
environments_utils/is_online.py
environments_utils/is_os.py
environments_utils/is_stdout_enabled.py
environments_utils/is_tmux.py
environments_utils.egg-info/PKG-INFO
environments_utils.egg-info/SOURCES.txt
environments_utils.egg-info/dependency_links.txt
environments_utils.egg-info/requires.txt
environments_utils.egg-info/top_level.txt