Metadata-Version: 2.1
Name: environments-utils
Version: 1.0.15
Summary: Utilities to identify which environments is your python script running within.
Home-page: https://github.com/LucaCappelletti94/environments_utils
Author: Luca Cappelletti
Author-email: cappelletti.luca94@gmail.com
License: MIT
Platform: UNKNOWN
Classifier: Development Status :: 5 - Production/Stable
Classifier: License :: OSI Approved :: MIT License
Classifier: Programming Language :: Python :: 3
Provides-Extra: test
License-File: LICENSE
